COPYING
MANIFEST.in
README.rst
pyproject.toml
setup.py
tox.ini
psycogreen/__init__.py
psycogreen/eventlet.py
psycogreen/gevent.py
psycogreen.egg-info/PKG-INFO
psycogreen.egg-info/SOURCES.txt
psycogreen.egg-info/dependency_links.txt
psycogreen.egg-info/top_level.txt
tests/requirements.txt
tests/test_eventlet.py
tests/test_gevent.py
tests/wait_server.py