Metadata-Version: 1.2
Name: psycogreen
Version: 1.0.2
Summary: psycopg2 integration with coroutine libraries
Home-page: https://github.com/psycopg/psycogreen/
Author: Daniele Varrazzo
Author-email: daniele.varrazzo@gmail.com
License: BSD
Project-URL: Funding, https://github.com/sponsors/dvarrazzo
Project-URL: Bug tracker, https://github.com/psycopg/psycogreen/issues
Platform: UNKNOWN
Classifier: Development Status :: 5 - Production/Stable
Classifier: License :: OSI Approved :: BSD License
Classifier: Operating System :: OS Independent
Classifier: Programming Language :: Python :: 2
Classifier: Programming Language :: Python :: 3
Classifier: Topic :: Database
